XStatic_Magic_Search-0.2.5.2-py3.5-nspkg.pth
xstatic/pkg/magic_search/__init__.py
xstatic/pkg/magic_search/data/magic_search.html
xstatic/pkg/magic_search/data/magic_search.js
xstatic/pkg/magic_search/data/magic_search.scss
XStatic_Magic_Search-0.2.5.2.dist-info/METADATA
XStatic_Magic_Search-0.2.5.2.dist-info/WHEEL
XStatic_Magic_Search-0.2.5.2.dist-info/namespace_packages.txt
XStatic_Magic_Search-0.2.5.2.dist-info/top_level.txt
XStatic_Magic_Search-0.2.5.2.dist-info/RECORD
