Metadata-Version: 2.1
Name: XStatic-Magic-Search
Version: 0.2.5.2
Summary: Magic-Search 0.2.5 (XStatic packaging standard)
Home-page: https://github.com/eucalyptus/magic-search
Maintainer: Randy Bertram
Maintainer-email: rbertram@us.ibm.com
License: (same as Magic-Search)
Keywords: magic_search xstatic
Platform: any
